{"info":{"_postman_id":"f6c41ba2-8792-40bc-80a6-b8165a59c1a2","name":"Map","schema":"https://schema.getpostman.com/json/collection/v2.1.0/collection.json"},"item":[{"name":"Get map","id":"746ecda0-d446-4c0c-b3a7-5e4e82e891f6","protocolProfileBehavior":{"disableBodyPruning":true},"request":{"method":"GET","header":[],"url":{"raw":"https://api.mapbox.com/v4/rayato159.7sun468w/14/{x}/{y}.png?access_token=pk.eyJ1IjoicmF5YXRvMTU5IiwiYSI6ImNrdmJpOHVuZDBkOXYyb2xxN2w2MnlmOGgifQ.4220wFT-2CX1QPy30P6V5Q","protocol":"https","host":["api","mapbox","com"],"path":["v4","rayato159.7sun468w","14","{x}","{y}.png"],"query":[{"key":"access_token","value":"pk.eyJ1IjoicmF5YXRvMTU5IiwiYSI6ImNrdmJpOHVuZDBkOXYyb2xxN2w2MnlmOGgifQ.4220wFT-2CX1QPy30P6V5Q"}]}},"response":[]}]}